flask_migratepg/__init__.py
flask_migratepg-1.0.3.dist-info/licenses/LICENSE
flask_migratepg-1.0.3.dist-info/METADATA
flask_migratepg-1.0.3.dist-info/WHEEL
flask_migratepg-1.0.3.dist-info/top_level.txt
flask_migratepg-1.0.3.dist-info/RECORD
