Metadata-Version: 2.4
Name: flask-migratepg
Version: 1.0.3
Summary: Simple migration command for Flask and Psycopg 3.
Author-email: Damien Bezborodov <dbezborodov@gmail.com>
Project-URL: Homepage, https://github.com/bezborodow/flask-migratepg
Project-URL: Bug Tracker, https://github.com/bezborodow/flask-migratepg/issues
Classifier: Programming Language :: Python :: 3
Classifier: License :: OSI Approved :: BSD License
Classifier: Operating System :: OS Independent
Classifier: Framework :: Flask
Requires-Python: >=3.7
License-File: LICENSE
Requires-Dist: flask>=3.0
Requires-Dist: psycopg>=3.1
Requires-Dist: click>=8.0.0
Dynamic: license-file
